fixings/__init__.py
fixings-0.0.0.dist-info/LICENSE
fixings-0.0.0.dist-info/METADATA
fixings-0.0.0.dist-info/WHEEL
fixings-0.0.0.dist-info/top_level.txt
fixings-0.0.0.dist-info/RECORD
